umar_py/__init__.py
umar_py/util/__init__.py
umar_py/util/file.py
umar_py-0.0.4.dist-info/LICENSE.txt
umar_py-0.0.4.dist-info/METADATA
umar_py-0.0.4.dist-info/WHEEL
umar_py-0.0.4.dist-info/top_level.txt
umar_py-0.0.4.dist-info/RECORD
